weldor/__init__.py
weldor/weldor.py
weldor/wordbase/index.txt
weldor/wordbase/shell.txt
weldor-2.8.2022.dist-info/LICENSE
weldor-2.8.2022.dist-info/METADATA
weldor-2.8.2022.dist-info/WHEEL
weldor-2.8.2022.dist-info/entry_points.txt
weldor-2.8.2022.dist-info/top_level.txt
weldor-2.8.2022.dist-info/RECORD
