Metadata-Version: 2.1
Name: weldor
Version: 2.8.2022
Summary: weldor - A reactive AI designed to assist you with Wordle variants
Home-page: https://github.com/ayaanhossain/weldor
Author: ayaanhossain
License: UNKNOWN
Project-URL: Bug Reports, https://github.com/ayaanhossain/weldor/issues
Project-URL: Source, https://github.com/ayaanhossain/weldor/tree/master/weldor
Keywords: reactive ai artificial intelligence entropy wordle trees sets wordle-solver wordle-python wordle-assistant wordle-solution wordle-game wordle-helper
Platform: UNKNOWN
Classifier: Development Status :: 4 - Beta
Classifier: Intended Audience :: Science/Research
Classifier: Topic :: Games/Entertainment :: Turn Based Strategy
Classifier: Topic :: Scientific/Engineering :: Artificial Intelligence
Classifier: License :: OSI Approved :: MIT License
Classifier: Programming Language :: Python :: 3.6
Classifier: Programming Language :: Python :: 3.7
Classifier: Programming Language :: Python :: 3.8
Classifier: Programming Language :: Python :: 3.9
Classifier: Programming Language :: Python :: 3.10
Requires-Python: !=2.7, !=3.0.*, !=3.1.*, !=3.2.*, !=3.3.*, !=3.4.*, !=3.5.*, >=3.6.*, <4.0.*
